wp_forge/__init__.py
wp_forge/backgrounds.json
wp_forge/client.py
wp_forge/icon.png
wp_forge/script.py
wp_forge-1.1.0.dist-info/licenses/LICENSE
wp_forge-1.1.0.dist-info/METADATA
wp_forge-1.1.0.dist-info/WHEEL
wp_forge-1.1.0.dist-info/entry_points.txt
wp_forge-1.1.0.dist-info/top_level.txt
wp_forge-1.1.0.dist-info/RECORD
